setup.py
resulter/__init__.py
resulter/resulter.py
resulter.egg-info/PKG-INFO
resulter.egg-info/SOURCES.txt
resulter.egg-info/dependency_links.txt
resulter.egg-info/top_level.txt