Metadata-Version: 1.0
Name: resulter
Version: 0.0.1
Summary: Library for make a code more clearly, more readable and more supportable
Home-page: UNKNOWN
Author: Nickolay Ovdienko
Author-email: Nickolay.Ovdienko@emc.com
License: MIT
Platform: UNKNOWN
